{
  "category": "topazium:items",
  "name": "topazium.entry.golem_legs_basic.name",
  "icon": "topazium:golem_legs_basic",
  "x": 5,
  "y": -3,
  "parents": [
    {
      "entry": "topazium:items/component_table"
    }
  ],
  "pages": [
    {
      "type": "modonomicon:spotlight",
      "item": "topazium:golem_legs_basic",
      "text": "topazium.page.golem_legs_basic.info"
    },
    {
      "type": "modonomicon:text",
      "title": "Utilisation",
      "text": "topazium.page.golem_legs_basic.usage"
    }
  ]
}
